hari_data/__init__.py
hari_data/cli/commands/cli.py
hari_data/cli/commands/contract.py
hari_data/cli/commands/project.py
hari_data/cli/templates/__templates__.py
hari_data/cli/templates/hari_template.py
hari_data/cli/templates/hari_template_configs.py
hari_data/cli/templates/hari_template_helpers.py
hari_data/cli/templates/hari_template_job.py
hari_data/cli/templates/hari_template_lock.py
hari_data/cli/templates/hari_template_readme.py
hari_data/cli/templates/hari_template_validators.py
hari_data/exceptions.py
hari_data/session/hari/hari_spark_session.py
hari_data/session/hari/hari_spark_session_generic.py
hari_data/session/hari_spark_session_manager.py
hari_data/utils/helpers.py
hari_data/utils/logger.py
hari_data/utils/validators.py
hari_data-0.1.5.dist-info/LICENSE
hari_data-0.1.5.dist-info/METADATA
hari_data-0.1.5.dist-info/WHEEL
hari_data-0.1.5.dist-info/entry_points.txt
hari_data-0.1.5.dist-info/RECORD
