Metadata-Version: 2.3
Name: hari-data
Version: 0.1.5
Summary: Hari is a Python library designed to establish a standardized pattern for developing PySpark applications, leveraging the concept of "data contracts" to ensure consistency, reliability, and maintainability in data engineering workflows.
License: MIT
Author: Julio Zeferino
Author-email: julioszeferino@gmail.com
Requires-Python: >=3.11,<4.0
Classifier: Topic :: Software Development :: Libraries :: Python Modules
Classifier: Topic :: Software Development :: Build Tools
Classifier: Topic :: Utilities
Classifier: Topic :: Scientific/Engineering :: Information Analysis
Classifier: Topic :: System :: Distributed Computing
Classifier: Environment :: Console
Classifier: Environment :: Plugins
Classifier: Intended Audience :: Developers
Classifier: Intended Audience :: Information Technology
Classifier: Natural Language :: English
Classifier: Development Status :: 5 - Production/Stable
Classifier: Programming Language :: Python :: 3.11
Requires-Dist: pyspark (==3.5.0)
Requires-Dist: pyyaml (>=6.0.2,<7.0.0)
Requires-Dist: rich (>=14.1.0,<15.0.0)
Requires-Dist: typer (>=0.16.0,<0.17.0)
Project-URL: Bug Tracker, https://github.com/julioszeferino/hari/issues
Project-URL: Documentation, https://hari-data.readthedocs.io/en/latest/
Project-URL: Donation, https://hari-data.readthedocs.io/en/latest/
Project-URL: Source Code, https://github.com/julioszeferino/hari
